ingot-0.0.0.dist-info/METADATA
ingot-0.0.0.dist-info/WHEEL
ingot/__init__.py
ingot-0.0.0.dist-info/RECORD
