Metadata-Version: 2.1
Name: ingot
Version: 0.0.0
Summary: Coming soon...
Requires-Python: >=3.10
